git_deps
