Metadata-Version: 1.1
Name: git-deps
Version: 1.1.0
Summary: automatically detect dependencies between git commits
Home-page: https://github.com/aspiers/git-deps
Author: Adam Spiers
Author-email: git@adamspiers.org
License: GPL-2+
Platform: UNKNOWN
Classifier: Development Status :: 4 - Beta
Classifier: Environment :: Console
Classifier: Environment :: Web Environment
Classifier: Framework :: Flask
Classifier: Intended Audience :: Developers
Classifier: License :: OSI Approved :: GNU General Public License v2 or later (GPLv2+)
Classifier: Natural Language :: English
Classifier: Operating System :: OS Independent
Classifier: Programming Language :: Python
Classifier: Topic :: Software Development :: Version Control
Classifier: Topic :: Utilities
